louis/__init__.py
Pylouis-0.0.1.dist-info/LICENSE
Pylouis-0.0.1.dist-info/METADATA
Pylouis-0.0.1.dist-info/WHEEL
Pylouis-0.0.1.dist-info/top_level.txt
Pylouis-0.0.1.dist-info/RECORD
