Metadata-Version: 2.1
Name: Pylouis
Version: 0.0.1
Summary: liblouis
Home-page: https://https://github.com/liblouis/liblouis
Author: Popovici Catalin
Author-email: cp@baum.ro
License: UNKNOWN
Platform: UNKNOWN
Classifier: Programming Language :: Python :: 3
Classifier: License :: OSI Approved :: MIT License
Classifier: Operating System :: OS Independent
Requires-Python: >=3.6
